cf_pretty_form_errors-1.0.4.dist-info/DESCRIPTION.rst
cf_pretty_form_errors-1.0.4.dist-info/RECORD
cf_pretty_form_errors-1.0.4.dist-info/zip-safe
cf_pretty_form_errors-1.0.4.dist-info/metadata.json
cf_pretty_form_errors-1.0.4.dist-info/METADATA
cf_pretty_form_errors-1.0.4.dist-info/WHEEL
cf_pretty_form_errors-1.0.4.dist-info/top_level.txt
cf_pretty_form_errors/apps.pyc
cf_pretty_form_errors/__init__.pyc
cf_pretty_form_errors/form_mixins.pyc
cf_pretty_form_errors/__init__.py
cf_pretty_form_errors/form_mixins.py
cf_pretty_form_errors/apps.py
cf_pretty_form_errors/templates/pretty_forms/bootstrap3/field.html
cf_pretty_form_errors/templates/pretty_forms/bootstrap3/layout/help_text_and_errors.html
cf_pretty_form_errors/static/pretty_forms/js/enable-form-tooltips.js
cf_pretty_form_errors/static/pretty_forms/js/bootstrap-tooltip.js
cf_pretty_form_errors/static/pretty_forms/js/jquery_extensions.js
cf_pretty_form_errors/static/pretty_forms/fonts/question-font/style.css
cf_pretty_form_errors/static/pretty_forms/fonts/question-font/fonts/question-font.ttf
cf_pretty_form_errors/static/pretty_forms/fonts/question-font/fonts/question-font.woff
cf_pretty_form_errors/static/pretty_forms/fonts/question-font/fonts/question-font.svg
cf_pretty_form_errors/static/pretty_forms/fonts/question-font/fonts/question-font.eot
cf_pretty_form_errors/static/pretty_forms/css/form-pretty-errors.css
cf_pretty_form_errors/static/pretty_forms/css/bootstrap-tooltip.css
